MANIFEST.in
README.rst
setup.py
docs/HISTORY.txt
docs/LICENSE.GPL
docs/LICENSE.txt
ftw/__init__.py
ftw.contentpage.egg-info/PKG-INFO
ftw.contentpage.egg-info/SOURCES.txt
ftw.contentpage.egg-info/dependency_links.txt
ftw.contentpage.egg-info/entry_points.txt
ftw.contentpage.egg-info/namespace_packages.txt
ftw.contentpage.egg-info/not-zip-safe
ftw.contentpage.egg-info/requires.txt
ftw.contentpage.egg-info/top_level.txt
ftw/contentpage/__init__.py
ftw/contentpage/adapters.py
ftw/contentpage/config.py
ftw/contentpage/configure.zcml
ftw/contentpage/extender.py
ftw/contentpage/geo.py
ftw/contentpage/hooks.py
ftw/contentpage/indexer.py
ftw/contentpage/interfaces.py
ftw/contentpage/lawgiver.zcml
ftw/contentpage/permissions.zcml
ftw/contentpage/testing.py
ftw/contentpage/vocabularies.py
ftw/contentpage/Extensions/__init__.py
ftw/contentpage/Extensions/install.py
ftw/contentpage/behaviors/__init__.py
ftw/contentpage/behaviors/configure.zcml
ftw/contentpage/behaviors/content_categories.py
ftw/contentpage/browser/__init__.py
ftw/contentpage/browser/address.pt
ftw/contentpage/browser/addressblock_detail_view.pt
ftw/contentpage/browser/addressblock_portlet_view.pt
ftw/contentpage/browser/addressblock_view.pt
ftw/contentpage/browser/addressblock_view.py
ftw/contentpage/browser/anchor.py
ftw/contentpage/browser/authorities.pt
ftw/contentpage/browser/authorities.py
ftw/contentpage/browser/baselisting.py
ftw/contentpage/browser/configure.zcml
ftw/contentpage/browser/eventlisting.pt
ftw/contentpage/browser/eventlisting.py
ftw/contentpage/browser/faq.pt
ftw/contentpage/browser/faq.py
ftw/contentpage/browser/feedback.py
ftw/contentpage/browser/flashupload.pt
ftw/contentpage/browser/flashupload.py
ftw/contentpage/browser/listingblock_gallery_view.pt
ftw/contentpage/browser/listingblock_gallery_view.py
ftw/contentpage/browser/listingblock_view.pt
ftw/contentpage/browser/listingblock_view.py
ftw/contentpage/browser/newslisting.pt
ftw/contentpage/browser/newslisting.py
ftw/contentpage/browser/newslisting_rss.pt
ftw/contentpage/browser/simplelayout_summary.py
ftw/contentpage/browser/subject_listing.pt
ftw/contentpage/browser/subject_listing.py
ftw/contentpage/browser/table-custom-template.pt
ftw/contentpage/browser/tabs.pt
ftw/contentpage/browser/tabs.py
ftw/contentpage/browser/teaser_block_view.pt
