Metadata-Version: 1.1
Name: ftw.contentpage
Version: 1.16.4
Summary: Contentpage based on Simplelayout for for web/intranet
Home-page: https://github.com/4teamwork/ftw.contentpage
Author: 4teamwork AG
Author-email: mailto:info@4teamwork.ch
License: GPL2
Keywords: ftw contentpage
Platform: UNKNOWN
Classifier: Framework :: Plone
Classifier: Framework :: Plone :: 4.2
Classifier: Framework :: Plone :: 4.3
Classifier: Programming Language :: Python
Classifier: Topic :: Software Development :: Libraries :: Python Modules
